sequence/__init__.py
sequence/app/__init__.py
sequence/app/random_request.py
sequence/app/request_app.py
sequence/app/teleport_app.py
sequence/components/__init__.py
sequence/components/beam_splitter.py
sequence/components/bsm.py
sequence/components/circuit.py
sequence/components/detector.py
sequence/components/fiber_stretcher.py
sequence/components/interferometer.py
sequence/components/light_source.py
sequence/components/memory.py
sequence/components/mirror.py
sequence/components/optical_channel.py
sequence/components/photon.py
sequence/components/spdc_lens.py
sequence/components/switch.py
sequence/components/transducer.py
sequence/components/transmon.py
sequence/constants.py
sequence/entanglement_management/__init__.py
sequence/entanglement_management/entanglement_protocol.py
sequence/entanglement_management/generation/__init__.py
sequence/entanglement_management/generation/barret_kok.py
sequence/entanglement_management/generation/generation_base.py
sequence/entanglement_management/generation/generation_message.py
sequence/entanglement_management/generation/single_heralded.py
sequence/entanglement_management/purification/__init__.py
sequence/entanglement_management/purification/bbpssw_bds.py
sequence/entanglement_management/purification/bbpssw_circuit.py
sequence/entanglement_management/purification/bbpssw_protocol.py
sequence/entanglement_management/swapping.py
sequence/entanglement_management/teleportation.py
sequence/gui/__init__.py
sequence/gui/app.py
sequence/gui/assets/argonne.png
sequence/gui/assets/attributions_req
sequence/gui/assets/bsmnode.png
sequence/gui/assets/detector.png
sequence/gui/assets/logo.png
sequence/gui/assets/photonsource.png
sequence/gui/assets/quantum.png
sequence/gui/assets/repeater.png
sequence/gui/assets/router.png
sequence/gui/assets/sequence.jpg
sequence/gui/assets/svg/bsmnode.svg
sequence/gui/assets/svg/detector.svg
sequence/gui/assets/svg/photonsource.svg
sequence/gui/assets/svg/quantum.svg
sequence/gui/assets/svg/repeater.svg
sequence-0.8.4.dist-info/WHEEL
sequence-0.8.4.dist-info/METADATA
sequence-0.8.4.dist-info/RECORD
