Metadata-Version: 2.3
Name: sequence
Version: 0.8.4
Summary: Simulator of QUantum Network Communication (SeQUeNCe) is an open-source tool that allows modeling of quantum networks including photonic network components, control protocols, and applications.
Keywords: quantum,network,discrete,event,simulator
Author: Xiaoliang Wu, Joaquin Chung, Alexander Kolar, Alexander Kiefer, Eugene Wang, Tian Zhong, Rajkumar Kettimuthu, Martin Suchara, Robert Hayek, Ansh Singal, Caitao Zhan
Author-email: Xiaoliang Wu, Joaquin Chung, Alexander Kolar, Alexander Kiefer, Eugene Wang, Tian Zhong, Rajkumar Kettimuthu, Martin Suchara, Robert Hayek, Ansh Singal, Caitao Zhan <czhan@anl.gov>
Classifier: Programming Language :: Python :: 3.11
Classifier: Programming Language :: Python :: 3.12
Classifier: Programming Language :: Python :: 3.13
Classifier: Programming Language :: Python :: 3.14
Requires-Dist: dash>=3.3.0
Requires-Dist: dash-bootstrap-components>=2.0.4
Requires-Dist: dash-core-components>=2.0.0
Requires-Dist: dash-cytoscape>=1.0.2
Requires-Dist: dash-html-components>=2.0.0
Requires-Dist: dash-table>=5.0.0
Requires-Dist: gmpy2>=2.2.2
Requires-Dist: ipywidgets>=8.1.8
Requires-Dist: jupyterlab>=4.5.0
Requires-Dist: matplotlib>=3.10.7
Requires-Dist: networkx>=3.6.1
Requires-Dist: numpy>=2.3.5
Requires-Dist: pandas>=2.3.3
Requires-Dist: plotly>=6.5.0
Requires-Dist: pytest>=9.0.2
Requires-Dist: qutip>=5.2.2
Requires-Dist: qutip-qip>=0.4.1
Requires-Dist: scipy>=1.16.3
Requires-Dist: tqdm>=4.67.1
Maintainer: Caitao Zhan, Robert Hayek
Maintainer-email: Caitao Zhan <czhan@anl.gov>, Robert Hayek <rhayek@anl.gov>
Requires-Python: >=3.11, <3.15
Project-URL: Changelog, https://github.com/sequence-toolbox/SeQUeNCe/blob/master/CHANGELOG.md
Project-URL: Documentation, https://sequence-rtd-tutorial.readthedocs.io/
Project-URL: Homepage, https://github.com/sequence-toolbox/SeQUeNCe
Project-URL: Issues, https://github.com/sequence-toolbox/SeQUeNCe/issues
